{"entry":[{"id":"c1","word":"i ще","english_equivalent":{"t":"and, moreover, in addition"},"orths":{"orth":[{"type":"cont","canonical":1,"onr":"1o1","part":[{"type":"phrasal","t":"i ще"}]}]},"syn":[{"cat":{"t":"subord_conj"},"sem":[{"pdtb3_relation":[{"sense":"succession"}]},{"pdtb3_relation":[{"sense":"conjunction"}]}]}]},{"id":"c2","word":"а","english_equivalent":{"t":"but"},"orths":{"orth":[{"type":"cont","canonical":1,"onr":"2o1","part":[{"type":"single","t":"а"}]}]},"syn":[{"cat":{"t":"coord_conj"},"sem":[{"pdtb3_relation":[{"sense":"contrast"}]},{"pdtb3_relation":[{"sense":"conjunction"}]},{"pdtb3_relation":[{"sense":"synchronous"}]}]}]},{"id":"c3","word":"а все-таки","english_equivalent":{"t":"however, after all, notwithstanding"},"orths":{"orth":[{"type":"cont","canonical":1,"onr":"3o1","part":[{"type":"phrasal","t":"а все-таки"}]},{"type":"cont","canonical":0,"onr":"3o2","part":[{"type":"phrasal","t":"а все ж таки"}]},{"type":"cont","canonical":0,"onr":"3o3","part":[{"type":"phrasal","t":"все таки"}]}]},"syn":[{"cat":{"t":"other"},"sem":[{"pdtb3_relation":[{"sense":"concession_arg2-as-denier"}]}]}]},{"id":"c4","word":"а саме","english_equivalent":{"t":"namely"},"orths":{"orth":[{"type":"cont","canonical":1,"onr":"4o1","part":[{"type":"phrasal","t":"а саме"}]}]},"syn":[{"cat":{"t":"adverb"},"sem":[{"pdtb3_relation":[{"sense":"equivalence"}]},{"pdtb3_relation":[{"sense":"instantiation_arg2-as-instance"}]}]}]},{"id":"c5","word":"а усе","english_equivalent":{"t":"however"},"orths":{"orth":[{"type":"cont","canonical":1,"onr":"5o1","part":[{"type":"phrasal","t":"а усе"}]}]},"syn":[{"cat":{"t":"other"},"sem":[{"pdtb3_relation":[{"sense":"concession_arg2-as-denier"}]}]}]},{"id":"c6","word":"а усе-таки","english_equivalent":{"t":"however, after all, notwithstanding"},"orths":{"orth":[{"type":"cont","canonical":1,"onr":"6o1","part":[{"type":"phrasal","t":"а усе-таки"}]}]},"syn":[{"cat":{"t":"other"},"sem":[{"pdtb3_relation":[{"sense":"concession_arg2-as-denier"}]}]}]},{"id":"c7","word":"аби","english_equivalent":{"t":"for, in order to"},"orths":{"orth":[{"type":"cont","canonical":1,"onr":"7o1","part":[{"type":"single","t":"аби"}]},{"type":"cont","canonical":0,"onr":"7o2","part":[{"type":"single","t":"аби-но"}]}]},"syn":[{"cat":{"t":"subord_conj"},"sem":[{"pdtb3_relation":[{"sense":"purpose_arg2-as-goal"}]}]}]},{"id":"c8","word":"або","english_equivalent":{"t":"or"},"orths":{"orth":[{"type":"cont","canonical":1,"onr":"8o1","part":[{"type":"single","t":"або"}]}]},"syn":[{"cat":{"t":"subord_conj"},"sem":[{"pdtb3_relation":[{"sense":"contrast"}]},{"pdtb3_relation":[{"sense":"disjunction"}]}]}]},{"id":"c9","word":"або...або","english_equivalent":{"t":"or...or"},"orths":{"orth":[{"type":"discont","canonical":1,"onr":"9o1","part":[{"type":"single","t":"або...або"}]}]},"syn":[{"cat":{"t":"other"},"sem":[{"pdtb3_relation":[{"sense":"disjunction"}]},{"pdtb3_relation":[{"sense":"substitution_arg1-as-subst"}]},{"pdtb3_relation":[{"sense":"similarity"}]}]}]},{"id":"c10","word":"адже","english_equivalent":{"t":"because"},"orths":{"orth":[{"type":"cont","canonical":1,"onr":"10o1","part":[{"type":"single","t":"адже"}]},{"type":"cont","canonical":0,"onr":"10o2","part":[{"type":"single","t":"адже ж"}]}]},"syn":[{"cat":{"t":"subord_conj"},"sem":[{"pdtb3_relation":[{"sense":"cause_reason"}]},{"pdtb3_relation":[{"sense":"contrast"}]}]}]},{"id":"c11","word":"аж","english_equivalent":{"t":"that, as, so (much) that"},"orths":{"orth":[{"type":"cont","canonical":1,"onr":"11o1","part":[{"type":"single","t":"аж"}]}]},"syn":[{"cat":{"t":"preposition"},"sem":[{"pdtb3_relation":[{"sense":"succession"}]},{"pdtb3_relation":[{"sense":"level-of-detail_arg1-as-detail"}]}]}]},{"id":"c12","word":"але","english_equivalent":{"t":"but"},"orths":{"orth":[{"type":"cont","canonical":1,"onr":"12o1","part":[{"type":"single","t":"але"}]}]},"syn":[{"cat":{"t":"coord_conj"},"sem":[{"pdtb3_relation":[{"sense":"contrast"}]},{"pdtb3_relation":[{"sense":"disjunction"}]},{"pdtb3_relation":[{"sense":"exception_arg1-as-excpt"}]}]}]},{"id":"c13","word":"ані...ані","english_equivalent":{"t":"neither...nor"},"orths":{"orth":[{"type":"discont","canonical":1,"onr":"13o1","part":[{"type":"single","t":"ані...ані"}]},{"type":"discont","canonical":0,"onr":"13o2","part":[{"type":"single","t":"ні...ні"}]}]},"syn":[{"cat":{"t":"coord_conj"},"sem":[{"pdtb3_relation":[{"sense":"contrast"}]},{"pdtb3_relation":[{"sense":"similarity"}]}]}]},{"id":"c14","word":"бiльше того","english_equivalent":{"t":"moreover, even"},"orths":{"orth":[{"type":"cont","canonical":1,"onr":"14o1","part":[{"type":"phrasal","t":"бiльше того"}]}]},"syn":[{"cat":{"t":"other"},"sem":[{"pdtb3_relation":[{"sense":"conjunction"}]},{"pdtb3_relation":[{"sense":"level-of-detail_arg1-as-detail"}]}]}]},{"id":"c15","word":"ба","english_equivalent":{"t":"even, moreover"},"orths":{"orth":[{"type":"cont","canonical":1,"onr":"15o1","part":[{"type":"single","t":"ба"}]},{"type":"cont","canonical":0,"onr":"15o2","part":[{"type":"single","t":"Ба більше"}]}]},"syn":[{"cat":{"t":"subord_conj"},"sem":[{"pdtb3_relation":[{"sense":"conjunction"}]},{"pdtb3_relation":[{"sense":"disjunction"}]},{"pdtb3_relation":[{"sense":"level-of-detail_arg1-as-detail"}]}]}]},{"id":"c16","word":"бо","english_equivalent":{"t":"because"},"orths":{"orth":[{"type":"cont","canonical":1,"onr":"16o1","part":[{"type":"single","t":"бо"}]}]},"syn":[{"cat":{"t":"subord_conj"},"sem":[{"pdtb3_relation":[{"sense":"cause_reason"}]}]}]},{"id":"c17","word":"буцім","english_equivalent":{"t":"as if"},"orths":{"orth":[{"type":"cont","canonical":1,"onr":"17o1","part":[{"type":"single","t":"буцім"}]},{"type":"cont","canonical":0,"onr":"17o2","part":[{"type":"single","t":"буцімто"}]}]},"syn":[{"cat":{"t":"adverb"},"sem":[{"pdtb3_relation":[{"sense":"similarity"}]}]}]},{"id":"c18","word":"в іншому випадку","english_equivalent":{"t":"otherwise"},"orths":{"orth":[{"type":"cont","canonical":1,"onr":"18o1","part":[{"type":"phrasal","t":"в іншому випадку"}]}]},"syn":[{"cat":{"t":"adverb"},"sem":[{"pdtb3_relation":[{"sense":"negCondition_arg1-as-negCond"}]},{"pdtb3_relation":[{"sense":"contrast"}]}]}]},{"id":"c19","word":"в той же час","english_equivalent":{"t":"while"},"orths":{"orth":[{"type":"cont","canonical":1,"onr":"19o1","part":[{"type":"phrasal","t":"в той же час"}]},{"type":"cont","canonical":0,"onr":"19o2","part":[{"type":"phrasal","t":"у той же час"}]}]},"syn":[{"cat":{"t":"coord_conj"},"sem":[{"pdtb3_relation":[{"sense":"synchronous"}]},{"pdtb3_relation":[{"sense":"contrast"}]}]}]},{"id":"c20","word":"в той час як","english_equivalent":{"t":"whereas"},"orths":{"orth":[{"type":"cont","canonical":1,"onr":"20o1","part":[{"type":"phrasal","t":"в той час як"}]}]},"syn":[{"cat":{"t":"subord_conj"},"sem":[{"pdtb3_relation":[{"sense":"contrast"}]},{"pdtb3_relation":[{"sense":"synchronous"}]}]}]},{"id":"c21","word":"втім","english_equivalent":{"t":"meanwhile, however"},"orths":{"orth":[{"type":"cont","canonical":1,"onr":"21o1","part":[{"type":"phrasal","t":"втім"}]},{"type":"cont","canonical":0,"onr":"21o2","part":[{"type":"phrasal","t":"утім"}]}]},"syn":[{"cat":{"t":"adverb"},"sem":[{"pdtb3_relation":[{"sense":"disjunction"}]},{"pdtb3_relation":[{"sense":"contrast"}]}]}]},{"id":"c22","word":"в цілому","english_equivalent":{"t":"overall"},"orths":{"orth":[{"type":"cont","canonical":1,"onr":"22o1","part":[{"type":"phrasal","t":"в цілому"}]}]},"syn":[{"cat":{"t":"adverb"},"sem":[{"pdtb3_relation":[{"sense":"level-of-detail_arg1-as-detail"}]}]}]},{"id":"c23","word":"вiдтак","english_equivalent":{"t":"hence"},"orths":{"orth":[{"type":"cont","canonical":1,"onr":"23o1","part":[{"type":"single","t":"вiдтак"}]}]},"syn":[{"cat":{"t":"adverb"},"sem":[{"pdtb3_relation":[{"sense":"cause_result"}]},{"pdtb3_relation":[{"sense":"succession"}]}]}]},{"id":"c24","word":"вже","english_equivalent":{"t":"already"},"orths":{"orth":[{"type":"cont","canonical":1,"onr":"24o1","part":[{"type":"single","t":"вже"}]}]},"syn":[{"cat":{"t":"adverb"},"sem":[{"pdtb3_relation":[{"sense":"precedence"}]}]}]},{"id":"c25","word":"відколи","english_equivalent":{"t":"since"},"orths":{"orth":[{"type":"cont","canonical":1,"onr":"25o1","part":[{"type":"single","t":"відколи"}]}]},"syn":[{"cat":{"t":"adverb"},"sem":[{"pdtb3_relation":[{"sense":"succession"}]}]}]},{"id":"c26","word":"відповідно","english_equivalent":{"t":"accordingly"},"orths":{"orth":[{"type":"cont","canonical":1,"onr":"26o1","part":[{"type":"single","t":"відповідно"}]}]},"syn":[{"cat":{"t":"adverb"},"sem":[{"pdtb3_relation":[{"sense":"cause_result"}]},{"pdtb3_relation":[{"sense":"similarity"}]},{"pdtb3_relation":[{"sense":"precedence"}]}]}]},{"id":"c27","word":"відразу","english_equivalent":{"t":"once"},"orths":{"orth":[{"type":"cont","canonical":1,"onr":"27o1","part":[{"type":"single","t":"відразу"}]}]},"syn":[{"cat":{"t":"adverb"},"sem":[{"pdtb3_relation":[{"sense":"synchronous"}]},{"pdtb3_relation":[{"sense":"precedence"}]}]}]},{"id":"c28","word":"взагалі","english_equivalent":{"t":"in general"},"orths":{"orth":[{"type":"cont","canonical":1,"onr":"28o1","part":[{"type":"single","t":"взагалі"}]}]},"syn":[{"cat":{"t":"adverb"},"sem":[{"pdtb3_relation":[{"sense":"level-of-detail_arg1-as-detail"}]}]}]},{"id":"c29","word":"врешті","english_equivalent":{"t":"ultimately"},"orths":{"orth":[{"type":"cont","canonical":1,"onr":"29o1","part":[{"type":"single","t":"врешті"}]},{"type":"cont","canonical":0,"onr":"29o2","part":[{"type":"single","t":"врешті-решт"}]}]},"syn":[{"cat":{"t":"adverb"},"sem":[{"pdtb3_relation":[{"sense":"precedence"}]},{"pdtb3_relation":[{"sense":"concession_arg1-as-denier"}]},{"pdtb3_relation":[{"sense":"level-of-detail_arg1-as-detail"}]}]}]},{"id":"c30","word":"все ж","english_equivalent":{"t":"although, on the other hand"},"orths":{"orth":[{"type":"cont","canonical":1,"onr":"30o1","part":[{"type":"phrasal","t":"все ж"}]}]},"syn":[{"cat":{"t":"other"},"sem":[{"pdtb3_relation":[{"sense":"contrast"}]},{"pdtb3_relation":[{"sense":"concession_arg1-as-denier"}]}]}]},{"id":"c31","word":"втім","english_equivalent":{"t":"however, on the other hand"},"orths":{"orth":[{"type":"cont","canonical":1,"onr":"31o1","part":[{"type":"single","t":"втім"}]}]},"syn":[{"cat":{"t":"adverb"},"sem":[{"pdtb3_relation":[{"sense":"concession_arg2-as-denier"}]}]}]},{"id":"c32","word":"гейби","english_equivalent":{"t":"as if"},"orths":{"orth":[{"type":"cont","canonical":1,"onr":"32o1","part":[{"type":"single","t":"гейби"}]}]},"syn":[{"cat":{"t":"subord_conj"},"sem":[{"pdtb3_relation":[{"sense":"similarity"}]}]}]},{"id":"c33","word":"дарма що","english_equivalent":{"t":"nevertheless, even so"},"orths":{"orth":[{"type":"cont","canonical":1,"onr":"33o1","part":[{"type":"phrasal","t":"дарма що"}]}]},"syn":[{"cat":{"t":"other"},"sem":[{"pdtb3_relation":[{"sense":"concession_arg2-as-denier"}]}]}]},{"id":"c34","word":"для того щоб","english_equivalent":{"t":"in order to"},"orths":{"orth":[{"type":"cont","canonical":1,"onr":"34o1","part":[{"type":"phrasal","t":"для того щоб"}]}]},"syn":[{"cat":{"t":"preposition"},"sem":[{"pdtb3_relation":[{"sense":"purpose_arg2-as-goal"}]}]}]},{"id":"c35","word":"до речi","english_equivalent":{"t":"by the way"},"orths":{"orth":[{"type":"cont","canonical":1,"onr":"35o1","part":[{"type":"phrasal","t":"до речi"}]}]},"syn":[{"cat":{"t":"other"},"sem":[{"pdtb3_relation":[{"sense":"synchronous"}]},{"pdtb3_relation":[{"sense":"exception_arg2-as-excpt"}]},{"pdtb3_relation":[{"sense":"level-of-detail_arg2-as-detail"}]}]}]},{"id":"c36","word":"до того","english_equivalent":{"t":"before"},"orths":{"orth":[{"type":"cont","canonical":1,"onr":"36o1","part":[{"type":"phrasal","t":"до того"}]},{"type":"cont","canonical":0,"onr":"36o2","part":[{"type":"phrasal","t":"до того ж"}]}]},"syn":[{"cat":{"t":"other"},"sem":[{"pdtb3_relation":[{"sense":"level-of-detail_arg2-as-detail"}]},{"pdtb3_relation":[{"sense":"precedence"}]}]}]},{"id":"c37","word":"доки","english_equivalent":{"t":"until"},"orths":{"orth":[{"type":"cont","canonical":1,"onr":"37o1","part":[{"type":"single","t":"доки"}]},{"type":"cont","canonical":0,"onr":"37o2","part":[{"type":"single","t":"допоки"}]}]},"syn":[{"cat":{"t":"adverb"},"sem":[{"pdtb3_relation":[{"sense":"precedence"}]},{"pdtb3_relation":[{"sense":"condition_arg2-as-cond"}]}]}]},{"id":"c38","word":"докіль","english_equivalent":{"t":"until, as long as"},"orths":{"orth":[{"type":"cont","canonical":1,"onr":"38o1","part":[{"type":"single","t":"докіль"}]}]},"syn":[{"cat":{"t":"subord_conj"},"sem":[{"pdtb3_relation":[{"sense":"precedence"}]},{"pdtb3_relation":[{"sense":"synchronous"}]}]}]},{"id":"c39","word":"допіру","english_equivalent":{"t":"until now, so far"},"orths":{"orth":[{"type":"cont","canonical":1,"onr":"39o1","part":[{"type":"single","t":"допіру"}]}]},"syn":[{"cat":{"t":"subord_conj"},"sem":[{"pdtb3_relation":[{"sense":"precedence"}]}]}]},{"id":"c40","word":"допоки","english_equivalent":{"t":"until"},"orths":{"orth":[{"type":"cont","canonical":1,"onr":"40o1","part":[{"type":"single","t":"допоки"}]},{"type":"cont","canonical":0,"onr":"40o2","part":[{"type":"single","t":"доки"}]}]},"syn":[{"cat":{"t":"adverb"},"sem":[{"pdtb3_relation":[{"sense":"precedence"}]},{"pdtb3_relation":[{"sense":"condition_arg2-as-cond"}]}]}]},{"id":"c41","word":"доти","english_equivalent":{"t":"until"},"orths":{"orth":[{"type":"cont ","canonical":1,"onr":"41o1","part":[{"type":"single","t":"доти"}]}]},"syn":[{"cat":{"t":"subord_conj"},"sem":[{"pdtb3_relation":[{"sense":"succession"}]},{"pdtb3_relation":[{"sense":"precedence"}]},{"pdtb3_relation":[{"sense":"condition_arg2-as-cond"}]}]}]},{"id":"c42","word":"до того ж","english_equivalent":{"t":"in addition"},"orths":{"orth":[{"type":"cont","canonical":1,"onr":"42o1","part":[{"type":"phrasal","t":"до того ж"}]}]},"syn":[{"cat":{"t":"other"},"sem":[{"pdtb3_relation":[{"sense":"level-of-detail_arg2-as-detail"}]},{"pdtb3_relation":[{"sense":"conjunction"}]}]}]},{"id":"c43","word":"завдяки","english_equivalent":{"t":"thanks to"},"orths":{"orth":[{"type":"cont","canonical":1,"onr":"43o1","part":[{"type":"single","t":"завдяки"}]}]},"syn":[{"cat":{"t":"preposition"},"sem":[{"pdtb3_relation":[{"sense":"cause_reason"}]},{"pdtb3_relation":[{"sense":"cause_result"}]}]}]},{"id":"c44","word":"за винятком","english_equivalent":{"t":"except"},"orths":{"orth":[{"type":"discont","canonical":1,"onr":"44o1","part":[{"type":"single","t":"за винятком"}]}]},"syn":[{"cat":{"t":"subord_conj"},"sem":[{"pdtb3_relation":[{"sense":"exception_arg2-as-excpt"}]},{"pdtb3_relation":[{"sense":"disjunction"}]}]}]},{"id":"c45","word":"замість","english_equivalent":{"t":"instead"},"orths":{"orth":[{"type":"cont","canonical":1,"onr":"45o1","part":[{"type":"single","t":"замість"}]}]},"syn":[{"cat":{"t":"preposition"},"sem":[{"pdtb3_relation":[{"sense":"substitution_arg2-as-subst"}]},{"pdtb3_relation":[{"sense":"contrast"}]},{"pdtb3_relation":[{"sense":"disjunction"}]}]}]},{"id":"c46","word":"зате","english_equivalent":{"t":"but"},"orths":{"orth":[{"type":"cont","canonical":1,"onr":"46o1","part":[{"type":"single","t":"зате"}]}]},"syn":[{"cat":{"t":"coord_conj"},"sem":[{"pdtb3_relation":[{"sense":"concession_arg2-as-denier"}]},{"pdtb3_relation":[{"sense":"contrast"}]}]}]},{"id":"c47","word":"згодом","english_equivalent":{"t":"later"},"orths":{"orth":[{"type":"cont","canonical":1,"onr":"47o1","part":[{"type":"single","t":"згодом"}]}]},"syn":[{"cat":{"t":"adverb"},"sem":[{"pdtb3_relation":[{"sense":"precedence"}]}]}]},{"id":"c48","word":"зокрема","english_equivalent":{"t":"in particular"},"orths":{"orth":[{"type":"cont","canonical":1,"onr":"48o1","part":[{"type":"single","t":"зокрема"}]}]},"syn":[{"cat":{"t":"adverb"},"sem":[{"pdtb3_relation":[{"sense":"level-of-detail_arg2-as-detail"}]},{"pdtb3_relation":[{"sense":"contrast"}]}]}]},{"id":"c49","word":"зрештою","english_equivalent":{"t":"in the end"},"orths":{"orth":[{"type":"cont","canonical":1,"onr":"49o1","part":[{"type":"single","t":"зрештою"}]}]},"syn":[{"cat":{"t":"adverb"},"sem":[{"pdtb3_relation":[{"sense":"precedence"}]},{"pdtb3_relation":[{"sense":"cause_result"}]},{"pdtb3_relation":[{"sense":"conjunction"}]}]}]},{"id":"c50","word":"і","english_equivalent":{"t":"and"},"orths":{"orth":[{"type":"cont","canonical":1,"onr":"50o1","part":[{"type":"single","t":"і"}]}]},"syn":[{"cat":{"t":"coord_conj"},"sem":[{"pdtb3_relation":[{"sense":"conjunction"}]},{"pdtb3_relation":[{"sense":"contrast"}]},{"pdtb3_relation":[{"sense":"synchronous"}]}]}]},{"id":"c51","word":"інакше","english_equivalent":{"t":"otherwise"},"orths":{"orth":[{"type":"cont","canonical":1,"onr":"51o1","part":[{"type":"single","t":"інакше"}]}]},"syn":[{"cat":{"t":"adverb"},"sem":[{"pdtb3_relation":[{"sense":"negCondition_arg1-as-negCond"}]},{"pdtb3_relation":[{"sense":"contrast"}]},{"pdtb3_relation":[{"sense":"exception_arg1-as-excpt"}]}]}]},{"id":"c52","word":"й","english_equivalent":{"t":"and"},"orths":{"orth":[{"type":"cont","canonical":1,"onr":"52o1","part":[{"type":"single","t":"й"}]}]},"syn":[{"cat":{"t":"coord_conj"},"sem":[{"pdtb3_relation":[{"sense":"conjunction"}]}]}]},{"id":"c53","word":"коли","english_equivalent":{"t":"when"},"orths":{"orth":[{"type":"cont","canonical":1,"onr":"53o1","part":[{"type":"single","t":"коли"}]},{"type":"cont","canonical":0,"onr":"53o2","part":[{"type":"single","t":"коли...то"}]}]},"syn":[{"cat":{"t":"subord_conj"},"sem":[{"pdtb3_relation":[{"sense":"synchronous"}]},{"pdtb3_relation":[{"sense":"condition_arg2-as-cond"}]},{"pdtb3_relation":[{"sense":"succession"}]}]}]},{"id":"c54","word":"коли ще","english_equivalent":{"t":"when else"},"orths":{"orth":[{"type":"cont","canonical":1,"onr":"54o1","part":[{"type":"phrasal","t":"коли ще"}]}]},"syn":[{"cat":{"t":"other"},"sem":[{"pdtb3_relation":[{"sense":"exception_arg1-as-excpt"}]},{"pdtb3_relation":[{"sense":"concession_arg1-as-denier"}]}]}]},{"id":"c55","word":"колись","english_equivalent":{"t":"once"},"orths":{"orth":[{"type":"cont","canonical":1,"onr":"55o1","part":[{"type":"single","t":"колись"}]}]},"syn":[{"cat":{"t":"adverb"},"sem":[{"pdtb3_relation":[{"sense":"succession"}]}]}]},{"id":"c56","word":"коротко кажучи","english_equivalent":{"t":"in short"},"orths":{"orth":[{"type":"cont","canonical":1,"onr":"56o1","part":[{"type":"phrasal","t":"коротко кажучи"}]}]},"syn":[{"cat":{"t":"other"},"sem":[{"pdtb3_relation":[{"sense":"equivalence"}]},{"pdtb3_relation":[{"sense":"level-of-detail_arg1-as-detail"}]}]}]},{"id":"c57","word":"крім того","english_equivalent":{"t":"besides"},"orths":{"orth":[{"type":"cont","canonical":1,"onr":"57o1","part":[{"type":"phrasal","t":"крім того"}]}]},"syn":[{"cat":{"t":"other"},"sem":[{"pdtb3_relation":[{"sense":"contrast"}]},{"pdtb3_relation":[{"sense":"level-of-detail_arg2-as-detail"}]},{"pdtb3_relation":[{"sense":"conjunction"}]}]}]},{"id":"c58","word":"лише","english_equivalent":{"t":"only"},"orths":{"orth":[{"type":"cont","canonical":1,"onr":"58o1","part":[{"type":"single","t":"лише"}]}]},"syn":[{"cat":{"t":"adverb"},"sem":[{"pdtb3_relation":[{"sense":"precedence"}]},{"pdtb3_relation":[{"sense":"exception_arg1-as-excpt"}]},{"pdtb3_relation":[{"sense":"condition_arg1-as-cond"}]}]}]},{"id":"c59","word":"мiж тим","english_equivalent":{"t":"meanwhile"},"orths":{"orth":[{"type":"cont","canonical":1,"onr":"59o1","part":[{"type":"phrasal","t":"мiж тим"}]}]},"syn":[{"cat":{"t":"adverb"},"sem":[{"pdtb3_relation":[{"sense":"synchronous"}]},{"pdtb3_relation":[{"sense":"conjunction"}]}]}]},{"id":"c60","word":"мов","english_equivalent":{"t":"as if"},"orths":{"orth":[{"type":"cont","canonical":1,"onr":"60o1","part":[{"type":"single","t":"мов"}]},{"type":"cont","canonical":0,"onr":"60o2","part":[{"type":"single","t":"мовбито"}]},{"type":"cont","canonical":0,"onr":"60o3","part":[{"type":"single","t":"мовби"}]}]},"syn":[{"cat":{"t":"subord_conj"},"sem":[{"pdtb3_relation":[{"sense":"similarity"}]},{"pdtb3_relation":[{"sense":"manner_arg2-as-manner"}]}]}]},{"id":"c61","word":"навіть","english_equivalent":{"t":"even"},"orths":{"orth":[{"type":"cont","canonical":1,"onr":"61o1","part":[{"type":"single","t":"навіть"}]}]},"syn":[{"cat":{"t":"adverb"},"sem":[{"pdtb3_relation":[{"sense":"level-of-detail_arg1-as-detail"}]}]}]},{"id":"c62","word":"наприклад","english_equivalent":{"t":"for example"},"orths":{"orth":[{"type":"cont","canonical":1,"onr":"62o1","part":[{"type":"single","t":"наприклад"}]}]},"syn":[{"cat":{"t":"adverb"},"sem":[{"pdtb3_relation":[{"sense":"instantiation_arg2-as-instance"}]},{"pdtb3_relation":[{"sense":"level-of-detail_arg2-as-detail"}]}]}]},{"id":"c63","word":"нарешті","english_equivalent":{"t":"finally"},"orths":{"orth":[{"type":"cont","canonical":1,"onr":"63o1","part":[{"type":"single","t":"нарешті"}]}]},"syn":[{"cat":{"t":"adverb"},"sem":[{"pdtb3_relation":[{"sense":"precedence"}]}]}]},{"id":"c64","word":"насправді","english_equivalent":{"t":"in fact"},"orths":{"orth":[{"type":"cont","canonical":1,"onr":"64o1","part":[{"type":"single","t":"насправді"}]}]},"syn":[{"cat":{"t":"adverb"},"sem":[{"pdtb3_relation":[{"sense":"contrast"}]},{"pdtb3_relation":[{"sense":"conjunction"}]}]}]},{"id":"c65","word":"настільки","english_equivalent":{"t":"so"},"orths":{"orth":[{"type":"cont","canonical":1,"onr":"65o1","part":[{"type":"single","t":"настільки"}]}]},"syn":[{"cat":{"t":"adverb"},"sem":[{"pdtb3_relation":[{"sense":"similarity"}]},{"pdtb3_relation":[{"sense":"level-of-detail_arg1-as-detail"}]},{"pdtb3_relation":[{"sense":"equivalence"}]}]}]},{"id":"c66","word":"натомість","english_equivalent":{"t":"instead"},"orths":{"orth":[{"type":"cont","canonical":1,"onr":"66o1","part":[{"type":"single","t":"натомість"}]}]},"syn":[{"cat":{"t":"adverb"},"sem":[{"pdtb3_relation":[{"sense":"contrast"}]}]}]},{"id":"c67","word":"наче","english_equivalent":{"t":"as if"},"orths":{"orth":[{"type":"cont","canonical":1,"onr":"67o1","part":[{"type":"single","t":"наче"}]},{"type":"cont","canonical":0,"onr":"67o2","part":[{"type":"single","t":"начеб"}]},{"type":"cont","canonical":0,"onr":"67o3","part":[{"type":"single","t":"начебто"}]}]},"syn":[{"cat":{"t":"subord_conj"},"sem":[{"pdtb3_relation":[{"sense":"similarity"}]}]}]},{"id":"c68","word":"не лише...а й","english_equivalent":{"t":"not only...but also"},"orths":{"orth":[{"type":"discont","canonical":1,"onr":"68o1","part":[{"type":"phrasal","t":"не лише...а й"}]},{"type":"discont","canonical":0,"onr":"68o2","part":[{"type":"phrasal","t":"не лише...але i"}]},{"type":"discont","canonical":0,"onr":"68o3","part":[{"type":"phrasal","t":"не лише...але й"}]},{"type":"discont","canonical":0,"onr":"68o4","part":[{"type":"phrasal","t":"не лише...а і"}]},{"type":"discont","canonical":0,"onr":"68o5","part":[{"type":"phrasal","t":"не лише...а"}]}]},"syn":[{"cat":{"t":"other"},"sem":[{"pdtb3_relation":[{"sense":"contrast"}]},{"pdtb3_relation":[{"sense":"similarity"}]},{"pdtb3_relation":[{"sense":"synchronous"}]}]}]},{"id":"c69","word":"не менш","english_equivalent":{"t":"nevertheless"},"orths":{"orth":[{"type":"cont","canonical":1,"onr":"69o1","part":[{"type":"phrasal","t":"не менш"}]},{"type":"cont","canonical":0,"onr":"69o2","part":[{"type":"phrasal","t":"не менше"}]}]},"syn":[{"cat":{"t":"adverb"},"sem":[{"pdtb3_relation":[{"sense":"similarity"}]},{"pdtb3_relation":[{"sense":"contrast"}]}]}]},{"id":"c70","word":"не менше","english_equivalent":{"t":"nevertheless"},"orths":{"orth":[{"type":"cont","canonical":1,"onr":"70o1","part":[{"type":"phrasal","t":"не менше"}]}]},"syn":[{"cat":{"t":"adverb"},"sem":[{"pdtb3_relation":[{"sense":"concession_arg2-as-denier"}]},{"pdtb3_relation":[{"sense":"conjunction"}]}]}]},{"id":"c71","word":"не тільки...а й","english_equivalent":{"t":"not only...but also"},"orths":{"orth":[{"type":"discont","canonical":1,"onr":"71o1","part":[{"type":"phrasal","t":"не тільки...а й"}]},{"type":"discont","canonical":0,"onr":"71o2","part":[{"type":"phrasal","t":"не тiльки...але й"}]},{"type":"discont","canonical":0,"onr":"71o3","part":[{"type":"phrasal","t":"не тiльки...але i"}]}]},"syn":[{"cat":{"t":"other"},"sem":[{"pdtb3_relation":[{"sense":"contrast"}]},{"pdtb3_relation":[{"sense":"similarity"}]},{"pdtb3_relation":[{"sense":"synchronous"}]}]}]},{"id":"c72","word":"незалежно від","english_equivalent":{"t":"regardless"},"orths":{"orth":[{"type":"discont","canonical":1,"onr":"72o1","part":[{"type":"single","t":"незалежно від"}]}]},"syn":[{"cat":{"t":"adverb"},"sem":[{"pdtb3_relation":[{"sense":"concession_arg2-as-denier"}]}]}]},{"id":"c73","word":"незважаючи на","english_equivalent":{"t":"regardless"},"orths":{"orth":[{"type":"discont","canonical":1,"onr":"73o1","part":[{"type":"single","t":"незважаючи на"}]}]},"syn":[{"cat":{"t":"adverb"},"sem":[{"pdtb3_relation":[{"sense":"contrast"}]},{"pdtb3_relation":[{"sense":"cause_negResult"}]},{"pdtb3_relation":[{"sense":"negCondition_arg2-as-negCond"}]}]}]},{"id":"c74","word":"немов","english_equivalent":{"t":"as if"},"orths":{"orth":[{"type":"cont","canonical":1,"onr":"74o1","part":[{"type":"single","t":"немов"}]},{"type":"cont","canonical":0,"onr":"74o2","part":[{"type":"single","t":"немовби"}]},{"type":"cont","canonical":0,"onr":"74o3","part":[{"type":"single","t":"немовбито"}]}]},"syn":[{"cat":{"t":"subord_conj"},"sem":[{"pdtb3_relation":[{"sense":"similarity"}]},{"pdtb3_relation":[{"sense":"manner_arg2-as-manner"}]}]}]},{"id":"c75","word":"неначе","english_equivalent":{"t":"as if"},"orths":{"orth":[{"type":"cont","canonical":1,"onr":"75o1","part":[{"type":"single","t":"неначе"}]},{"type":"cont","canonical":0,"onr":"75o2","part":[{"type":"single","t":"неначебто"}]}]},"syn":[{"cat":{"t":"subord_conj"},"sem":[{"pdtb3_relation":[{"sense":"similarity"}]},{"pdtb3_relation":[{"sense":"manner_arg2-as-manner"}]}]}]},{"id":"c76","word":"нехай","english_equivalent":{"t":"let, may"},"orths":{"orth":[{"type":"cont","canonical":1,"onr":"76o1","part":[{"type":"single","t":"нехай"}]},{"type":"cont","canonical":0,"onr":"76o2","part":[{"type":"single","t":"нехай-но"}]}]},"syn":[{"cat":{"t":"subord_conj"},"sem":[{"pdtb3_relation":[{"sense":"condition_arg1-as-cond"}]},{"pdtb3_relation":[{"sense":"purpose_arg2-as-goal"}]}]}]},{"id":"c77","word":"ніби","english_equivalent":{"t":"as if"},"orths":{"orth":[{"type":"cont","canonical":1,"onr":"77o1","part":[{"type":"single","t":"ніби"}]}]},"syn":[{"cat":{"t":"subord_conj"},"sem":[{"pdtb3_relation":[{"sense":"similarity"}]}]}]},{"id":"c78","word":"нібито","english_equivalent":{"t":"as if"},"orths":{"orth":[{"type":"cont","canonical":1,"onr":"78o1","part":[{"type":"single","t":"нібито"}]}]},"syn":[{"cat":{"t":"adverb"},"sem":[{"pdtb3_relation":[{"sense":"similarity"}]}]}]},{"id":"c79","word":"ніж","english_equivalent":{"t":"than,lest"},"orths":{"orth":[{"type":"cont","canonical":1,"onr":"79o1","part":[{"type":"single","t":"ніж"}]}]},"syn":[{"cat":{"t":"subord_conj"},"sem":[{"pdtb3_relation":[{"sense":"negCondition_arg1-as-negCond"}]}]}]},{"id":"c80","word":"однак","english_equivalent":{"t":"however"},"orths":{"orth":[{"type":"cont","canonical":1,"onr":"80o1","part":[{"type":"single","t":"однак"}]}]},"syn":[{"cat":{"t":"coord_conj"},"sem":[{"pdtb3_relation":[{"sense":"contrast"}]},{"pdtb3_relation":[{"sense":"conjunction"}]},{"pdtb3_relation":[{"sense":"concession_arg2-as-denier"}]}]}]},{"id":"c81","word":"одначе","english_equivalent":{"t":"however"},"orths":{"orth":[{"type":"cont","canonical":1,"onr":"81o1","part":[{"type":"single","t":"одначе"}]}]},"syn":[{"cat":{"t":"subord_conj"},"sem":[{"pdtb3_relation":[{"sense":"concession_arg2-as-denier"}]}]}]},{"id":"c82","word":"одночасно","english_equivalent":{"t":"simultaneously"},"orths":{"orth":[{"type":"cont","canonical":1,"onr":"82o1","part":[{"type":"single","t":"одночасно"}]}]},"syn":[{"cat":{"t":"adverb"},"sem":[{"pdtb3_relation":[{"sense":"synchronous"}]},{"pdtb3_relation":[{"sense":"conjunction"}]},{"pdtb3_relation":[{"sense":"similarity"}]}]}]},{"id":"c83","word":"окремо","english_equivalent":{"t":"separately"},"orths":{"orth":[{"type":"cont","canonical":1,"onr":"83o1","part":[{"type":"single","t":"окремо"}]}]},"syn":[{"cat":{"t":"adverb"},"sem":[{"pdtb3_relation":[{"sense":"level-of-detail_arg2-as-detail"}]},{"pdtb3_relation":[{"sense":"contrast"}]}]}]},{"id":"c84","word":"окрім","english_equivalent":{"t":"besides"},"orths":{"orth":[{"type":"cont","canonical":1,"onr":"84o1","part":[{"type":"single","t":"окрім"}]}]},"syn":[{"cat":{"t":"preposition"},"sem":[{"pdtb3_relation":[{"sense":"exception_arg2-as-excpt"}]},{"pdtb3_relation":[{"sense":"disjunction"}]}]}]},{"id":"c85","word":"оскільки","english_equivalent":{"t":"since"},"orths":{"orth":[{"type":"cont","canonical":1,"onr":"85o1","part":[{"type":"single","t":"оскільки"}]}]},"syn":[{"cat":{"t":"coord_conj"},"sem":[{"pdtb3_relation":[{"sense":"cause_reason"}]}]}]},{"id":"c86","word":"ось чому","english_equivalent":{"t":"that's why"},"orths":{"orth":[{"type":"cont","canonical":1,"onr":"86o1","part":[{"type":"phrasal","t":"ось чому"}]}]},"syn":[{"cat":{"t":"other"},"sem":[{"pdtb3_relation":[{"sense":"cause_reason"}]},{"pdtb3_relation":[{"sense":"level-of-detail_arg1-as-detail"}]}]}]},{"id":"c87","word":"отже","english_equivalent":{"t":"so"},"orths":{"orth":[{"type":"cont","canonical":1,"onr":"87o1","part":[{"type":"single","t":"отже"}]}]},"syn":[{"cat":{"t":"adverb"},"sem":[{"pdtb3_relation":[{"sense":"cause_result"}]},{"pdtb3_relation":[{"sense":"cause_reason"}]},{"pdtb3_relation":[{"sense":"level-of-detail_arg2-as-detail"}]}]}]},{"id":"c88","word":"отож","english_equivalent":{"t":"so"},"orths":{"orth":[{"type":"cont","canonical":1,"onr":"88o1","part":[{"type":"single","t":"отож"}]},{"type":"cont","canonical":0,"onr":"88o2","part":[{"type":"single","t":"отож-то"}]}]},"syn":[{"cat":{"t":"subord_conj"},"sem":[{"pdtb3_relation":[{"sense":"cause_result"}]}]}]},{"id":"c89","word":"перед","english_equivalent":{"t":"before"},"orths":{"orth":[{"type":"cont","canonical":1,"onr":"89o1","part":[{"type":"single","t":"перед"}]}]},"syn":[{"cat":{"t":"preposition"},"sem":[{"pdtb3_relation":[{"sense":"precedence"}]}]}]},{"id":"c90","word":"перш ніж","english_equivalent":{"t":"before"},"orths":{"orth":[{"type":"cont","canonical":1,"onr":"90o1","part":[{"type":"phrasal","t":"перш ніж"}]},{"type":"cont","canonical":0,"onr":"90o2","part":[{"type":"phrasal","t":"перше ніж"}]}]},"syn":[{"cat":{"t":"subord_conj"},"sem":[{"pdtb3_relation":[{"sense":"precedence"}]}]}]},{"id":"c91","word":"перш за все","english_equivalent":{"t":"above all, in the very beginning, before anything else"},"orths":{"orth":[{"type":"cont","canonical":1,"onr":"91o1","part":[{"type":"phrasal","t":"перш за все"}]}]},"syn":[{"cat":{"t":"other"},"sem":[{"pdtb3_relation":[{"sense":"precedence"}]}]}]},{"id":"c92","word":"під час того","english_equivalent":{"t":"while, in the meantime"},"orths":{"orth":[{"type":"cont","canonical":1,"onr":"92o1","part":[{"type":"phrasal","t":"під час того"}]}]},"syn":[{"cat":{"t":"subord_conj"},"sem":[{"pdtb3_relation":[{"sense":"synchronous"}]}]}]},{"id":"c93","word":"пізніше","english_equivalent":{"t":"later"},"orths":{"orth":[{"type":"cont","canonical":1,"onr":"93o1","part":[{"type":"single","t":"пізніше"}]}]},"syn":[{"cat":{"t":"adverb"},"sem":[{"pdtb3_relation":[{"sense":"precedence"}]}]}]},{"id":"c94","word":"після","english_equivalent":{"t":"later"},"orths":{"orth":[{"type":"cont","canonical":1,"onr":"94o1","part":[{"type":"single","t":"після"}]}]},"syn":[{"cat":{"t":"preposition"},"sem":[{"pdtb3_relation":[{"sense":"cause_result"}]},{"pdtb3_relation":[{"sense":"succession"}]}]}]},{"id":"c95","word":"плюс","english_equivalent":{"t":"plus"},"orths":{"orth":[{"type":"cont","canonical":1,"onr":"95o1","part":[{"type":"single","t":"плюс"}]}]},"syn":[{"cat":{"t":"coord_conj"},"sem":[{"pdtb3_relation":[{"sense":"conjunction"}]},{"pdtb3_relation":[{"sense":"level-of-detail_arg2-as-detail"}]}]}]},{"id":"c96","word":"по тому","english_equivalent":{"t":"later"},"orths":{"orth":[{"type":"cont","canonical":1,"onr":"96o1","part":[{"type":"phrasal","t":"по тому"}]}]},"syn":[{"cat":{"t":"adverb"},"sem":[{"pdtb3_relation":[{"sense":"precedence"}]}]}]},{"id":"c97","word":"по-друге","english_equivalent":{"t":"firstly"},"orths":{"orth":[{"type":"cont","canonical":1,"onr":"97o1","part":[{"type":"single","t":"по-друге"}]}]},"syn":[{"cat":{"t":"adverb"},"sem":[{"pdtb3_relation":[{"sense":"succession"}]},{"pdtb3_relation":[{"sense":"conjunction"}]}]}]},{"id":"c98","word":"по-перше","english_equivalent":{"t":"secondly"},"orths":{"orth":[{"type":"cont","canonical":1,"onr":"98o1","part":[{"type":"single","t":"по-перше"}]}]},"syn":[{"cat":{"t":"adverb"},"sem":[{"pdtb3_relation":[{"sense":"precedence"}]},{"pdtb3_relation":[{"sense":"conjunction"}]}]}]},{"id":"c99","word":"позаяк","english_equivalent":{"t":"since"},"orths":{"orth":[{"type":"cont","canonical":1,"onr":"99o1","part":[{"type":"single","t":"позаяк"}]}]},"syn":[{"cat":{"t":"subord_conj"},"sem":[{"pdtb3_relation":[{"sense":"cause_reason"}]}]}]},{"id":"c100","word":"поки","english_equivalent":{"t":"until"},"orths":{"orth":[{"type":"cont","canonical":1,"onr":"100o1","part":[{"type":"single","t":"поки"}]}]},"syn":[{"cat":{"t":"subord_conj"},"sem":[{"pdtb3_relation":[{"sense":"synchronous"}]},{"pdtb3_relation":[{"sense":"condition_arg1-as-cond"}]}]}]},{"id":"c101","word":"поки що","english_equivalent":{"t":"yet,still"},"orths":{"orth":[{"type":"cont","canonical":1,"onr":"101o1","part":[{"type":"pharsal","t":"поки що"}]}]},"syn":[{"cat":{"t":"adverb"},"sem":[{"pdtb3_relation":[{"sense":"synchronous"}]},{"pdtb3_relation":[{"sense":"manner_arg1-as-manner"}]},{"pdtb3_relation":[{"sense":"level-of-detail_arg2-as-detail"}]}]}]},{"id":"c102","word":"попри це","english_equivalent":{"t":"despite the fact"},"orths":{"orth":[{"type":"cont","canonical":1,"onr":"102o1","part":[{"type":"phrasal","t":"попри це"}]}]},"syn":[{"cat":{"t":"preposition"},"sem":[{"pdtb3_relation":[{"sense":"concession_arg1-as-denier"}]},{"pdtb3_relation":[{"sense":"condition_arg2-as-cond"}]},{"pdtb3_relation":[{"sense":"disjunction"}]}]}]},{"id":"c103","word":"поруч з","english_equivalent":{"t":"next"},"orths":{"orth":[{"type":"cont","canonical":1,"onr":"103o1","part":[{"type":"phrasal","t":"поруч з"}]}]},"syn":[{"cat":{"t":"adverb"},"sem":[{"pdtb3_relation":[{"sense":"conjunction"}]},{"pdtb3_relation":[{"sense":"synchronous"}]}]}]},{"id":"c104","word":"по суті","english_equivalent":{"t":"basically"},"orths":{"orth":[{"type":"cont","canonical":1,"onr":"104o1","part":[{"type":"phrasal","t":"по суті"}]}]},"syn":[{"cat":{"t":"adverb"},"sem":[{"pdtb3_relation":[{"sense":"equivalence"}]}]}]},{"id":"c105","word":"потім","english_equivalent":{"t":"then"},"orths":{"orth":[{"type":"cont","canonical":1,"onr":"105o1","part":[{"type":"single","t":"потім"}]}]},"syn":[{"cat":{"t":"adverb"},"sem":[{"pdtb3_relation":[{"sense":"precedence"}]}]}]},{"id":"c106","word":"при цьому","english_equivalent":{"t":"herewith"},"orths":{"orth":[{"type":"cont","canonical":1,"onr":"106o1","part":[{"type":"phrasal","t":"при цьому"}]}]},"syn":[{"cat":{"t":"adverb"},"sem":[{"pdtb3_relation":[{"sense":"contrast"}]},{"pdtb3_relation":[{"sense":"disjunction"}]}]}]},{"id":"c107","word":"притім","english_equivalent":{"t":"besides,moreover"},"orths":{"orth":[{"type":"cont","canonical":1,"onr":"107o1","part":[{"type":"single","t":"притім"}]}]},"syn":[{"cat":{"t":"subord_conj"},"sem":[{"pdtb3_relation":[{"sense":"conjunction"}]}]}]},{"id":"c108","word":"притому","english_equivalent":{"t":"besides"},"orths":{"orth":[{"type":"cont","canonical":1,"onr":"108o1","part":[{"type":"single","t":"притому"}]}]},"syn":[{"cat":{"t":"subord_conj"},"sem":[{"pdtb3_relation":[{"sense":"conjunction"}]}]}]},{"id":"c109","word":"причім","english_equivalent":{"t":"besides, moreover"},"orths":{"orth":[{"type":"cont","canonical":1,"onr":"109o1","part":[{"type":"single","t":"причім"}]},{"type":"cont","canonical":0,"onr":"109o2","part":[{"type":"single","t":"причому"}]}]},"syn":[{"cat":{"t":"subord_conj"},"sem":[{"pdtb3_relation":[{"sense":"conjunction"}]}]}]},{"id":"c110","word":"проте","english_equivalent":{"t":"but"},"orths":{"orth":[{"type":"cont","canonical":1,"onr":"110o1","part":[{"type":"single","t":"проте"}]}]},"syn":[{"cat":{"t":"coord_conj"},"sem":[{"pdtb3_relation":[{"sense":"contrast"}]}]}]},{"id":"c111","word":"радше","english_equivalent":{"t":"rather"},"orths":{"orth":[{"type":"cont","canonical":1,"onr":"111o1","part":[{"type":"single","t":"радше"}]}]},"syn":[{"cat":{"t":"adverb"},"sem":[{"pdtb3_relation":[{"sense":"substitution_arg2-as-subst"}]},{"pdtb3_relation":[{"sense":"level-of-detail_arg2-as-detail"}]}]}]},{"id":"c112","word":"раз","english_equivalent":{"t":"if, in case"},"orths":{"orth":[{"type":"cont","canonical":1,"onr":"112o1","part":[{"type":"single","t":"раз"}]}]},"syn":[{"cat":{"t":"subord_conj"},"sem":[{"pdtb3_relation":[{"sense":"condition_arg2-as-cond"}]}]}]},{"id":"c113","word":"раніше","english_equivalent":{"t":"before"},"orths":{"orth":[{"type":"cont","canonical":1,"onr":"113o1","part":[{"type":"single","t":"раніше"}]}]},"syn":[{"cat":{"t":"adverb"},"sem":[{"pdtb3_relation":[{"sense":"succession"}]}]}]},{"id":"c114","word":"себто","english_equivalent":{"t":"namely,that is"},"orths":{"orth":[{"type":"cont","canonical":1,"onr":"114o1","part":[{"type":"single","t":"себто"}]}]},"syn":[{"cat":{"t":"subord_conj"},"sem":[{"pdtb3_relation":[{"sense":"equivalence"}]}]}]},{"id":"c115","word":"скоріше","english_equivalent":{"t":"rather"},"orths":{"orth":[{"type":"cont","canonical":1,"onr":"115o1","part":[{"type":"single","t":"скоріше"}]}]},"syn":[{"cat":{"t":"adverb"},"sem":[{"pdtb3_relation":[{"sense":"contrast"}]},{"pdtb3_relation":[{"sense":"substitution_arg2-as-subst"}]}]}]},{"id":"c116","word":"та","english_equivalent":{"t":"and"},"orths":{"orth":[{"type":"cont","canonical":1,"onr":"116o1","part":[{"type":"single","t":"та"}]}]},"syn":[{"cat":{"t":"coord_conj"},"sem":[{"pdtb3_relation":[{"sense":"conjunction"}]},{"pdtb3_relation":[{"sense":"precedence"}]}]}]},{"id":"c117","word":"та все-таки","english_equivalent":{"t":"however"},"orths":{"orth":[{"type":"cont","canonical":1,"onr":"117o1","part":[{"type":"phrasal","t":"та все-таки"}]}]},"syn":[{"cat":{"t":"other"},"sem":[{"pdtb3_relation":[{"sense":"concession_arg2-as-denier"}]}]}]},{"id":"c118","word":"та усе","english_equivalent":{"t":"however"},"orths":{"orth":[{"type":"cont","canonical":1,"onr":"118o1","part":[{"type":"phrasal","t":"та усе"}]}]},"syn":[{"cat":{"t":"other"},"sem":[{"pdtb3_relation":[{"sense":"concession_arg2-as-denier"}]}]}]},{"id":"c119","word":"та усе-таки","english_equivalent":{"t":"however, in the end"},"orths":{"orth":[{"type":"cont","canonical":1,"onr":"119o1","part":[{"type":"phrasal","t":"та усе-таки"}]}]},"syn":[{"cat":{"t":"other"},"sem":[{"pdtb3_relation":[{"sense":"concession_arg2-as-denier"}]},{"pdtb3_relation":[{"sense":"precedence"}]}]}]},{"id":"c120","word":"таж","english_equivalent":{"t":"because, so"},"orths":{"orth":[{"type":"cont","canonical":1,"onr":"120o1","part":[{"type":"single","t":"таж"}]}]},"syn":[{"cat":{"t":"subord_conj"},"sem":[{"pdtb3_relation":[{"sense":"cause_result"}]}]}]},{"id":"c121","word":"так","english_equivalent":{"t":"but"},"orths":{"orth":[{"type":"cont","canonical":1,"onr":"121o1","part":[{"type":"single","t":"так"}]}]},"syn":[{"cat":{"t":"subord_conj"},"sem":[{"pdtb3_relation":[{"sense":"contrast"}]}]}]},{"id":"c122","word":"так само","english_equivalent":{"t":"similarly"},"orths":{"orth":[{"type":"cont","canonical":1,"onr":"122o1","part":[{"type":"phrasal","t":"так само"}]}]},"syn":[{"cat":{"t":"adverb"},"sem":[{"pdtb3_relation":[{"sense":"similarity"}]},{"pdtb3_relation":[{"sense":"manner_arg1-as-manner"}]}]}]},{"id":"c123","word":"так само...як i","english_equivalent":{"t":"similarly"},"orths":{"orth":[{"type":"discont","canonical":1,"onr":"123o1","part":[{"type":"phrasal","t":"так само...як i"}]}]},"syn":[{"cat":{"t":"adverb"},"sem":[{"pdtb3_relation":[{"sense":"similarity"}]},{"pdtb3_relation":[{"sense":"manner_arg1-as-manner"}]}]}]},{"id":"c124","word":"так що","english_equivalent":{"t":"so that"},"orths":{"orth":[{"type":"cont","canonical":1,"onr":"124o1","part":[{"type":"phrasal","t":"так що"}]}]},"syn":[{"cat":{"t":"subord_conj"},"sem":[{"pdtb3_relation":[{"sense":"cause_result"}]}]}]},{"id":"c125","word":"таки","english_equivalent":{"t":"still, after all"},"orths":{"orth":[{"type":"cont","canonical":1,"onr":"125o1","part":[{"type":"single","t":"таки"}]}]},"syn":[{"cat":{"t":"adverb"},"sem":[{"pdtb3_relation":[{"sense":"concession_arg1-as-denier"}]},{"pdtb3_relation":[{"sense":"concession_arg2-as-denier"}]},{"pdtb3_relation":[{"sense":"manner_arg1-as-manner"}]}]}]},{"id":"c126","word":"таким чином","english_equivalent":{"t":"thus"},"orths":{"orth":[{"type":"cont","canonical":1,"onr":"126o1","part":[{"type":"phrasal","t":"таким чином"}]}]},"syn":[{"cat":{"t":"other"},"sem":[{"pdtb3_relation":[{"sense":"cause_result"}]},{"pdtb3_relation":[{"sense":"manner_arg1-as-manner"}]}]}]},{"id":"c127","word":"також","english_equivalent":{"t":"also"},"orths":{"orth":[{"type":"cont","canonical":1,"onr":"127o1","part":[{"type":"single","t":"також"}]}]},"syn":[{"cat":{"t":"adverb"},"sem":[{"pdtb3_relation":[{"sense":"conjunction"}]},{"pdtb3_relation":[{"sense":"similarity"}]}]}]},{"id":"c128","word":"теж","english_equivalent":{"t":"also"},"orths":{"orth":[{"type":"cont","canonical":1,"onr":"128o1","part":[{"type":"single","t":"теж"}]}]},"syn":[{"cat":{"t":"adverb"},"sem":[{"pdtb3_relation":[{"sense":"synchronous"}]},{"pdtb3_relation":[{"sense":"conjunction"}]}]}]},{"id":"c129","word":"тим бiльше","english_equivalent":{"t":"moreover, futhermore"},"orths":{"orth":[{"type":"cont","canonical":1,"onr":"129o1","part":[{"type":"phrasal","t":"тим бiльше"}]}]},"syn":[{"cat":{"t":"adverb"},"sem":[{"pdtb3_relation":[{"sense":"level-of-detail_arg1-as-detail"}]},{"pdtb3_relation":[{"sense":"level-of-detail_arg2-as-detail"}]}]}]},{"id":"c130","word":"тим не менше","english_equivalent":{"t":"nevertheless"},"orths":{"orth":[{"type":"cont","canonical":1,"onr":"130o1","part":[{"type":"phrasal","t":"тим не менше"}]}]},"syn":[{"cat":{"t":"adverb"},"sem":[{"pdtb3_relation":[{"sense":"contrast"}]},{"pdtb3_relation":[{"sense":"instantiation_arg1-as-instance"}]}]}]},{"id":"c131","word":"тим самим","english_equivalent":{"t":"thereby"},"orths":{"orth":[{"type":"cont","canonical":1,"onr":"131o1","part":[{"type":"phrasal","t":"тим самим"}]}]},"syn":[{"cat":{"t":"other"},"sem":[{"pdtb3_relation":[{"sense":"cause_result"}]},{"pdtb3_relation":[{"sense":"equivalence"}]}]}]},{"id":"c132","word":"тим часом","english_equivalent":{"t":"meantime"},"orths":{"orth":[{"type":"cont","canonical":1,"onr":"132o1","part":[{"type":"phrasal","t":"тим часом"}]},{"type":"cont","canonical":0,"onr":"132o2","part":[{"type":"phrasal","t":"тим самим часом"}]}]},"syn":[{"cat":{"t":"other"},"sem":[{"pdtb3_relation":[{"sense":"synchronous"}]},{"pdtb3_relation":[{"sense":"conjunction"}]},{"pdtb3_relation":[{"sense":"contrast"}]}]}]},{"id":"c133","word":"тільки","english_equivalent":{"t":"but, if, just, only"},"orths":{"orth":[{"type":"cont","canonical":1,"onr":"133o1","part":[{"type":"single","t":"тільки"}]},{"type":"cont","canonical":0,"onr":"133o2","part":[{"type":"single","t":"тільки-но"}]}]},"syn":[{"cat":{"t":"subord_conj"},"sem":[{"pdtb3_relation":[{"sense":"concession_arg2-as-denier"}]}]}]},{"id":"c134","word":"то","english_equivalent":{"t":"then"},"orths":{"orth":[{"type":"cont","canonical":1,"onr":"134o1","part":[{"type":"single","t":"то"}]}]},"syn":[{"cat":{"t":"subord_conj"},"sem":[{"pdtb3_relation":[{"sense":"condition_arg1-as-cond"}]},{"pdtb3_relation":[{"sense":"cause_result"}]}]}]},{"id":"c135","word":"тобто","english_equivalent":{"t":"namely"},"orths":{"orth":[{"type":"cont","canonical":1,"onr":"135o1","part":[{"type":"single","t":"тобто"}]}]},"syn":[{"cat":{"t":"subord_conj"},"sem":[{"pdtb3_relation":[{"sense":"instantiation_arg2-as-instance"}]}]}]},{"id":"c136","word":"тоді","english_equivalent":{"t":"then"},"orths":{"orth":[{"type":"cont","canonical":1,"onr":"136o1","part":[{"type":"single","t":"тоді"}]}]},"syn":[{"cat":{"t":"adverb"},"sem":[{"pdtb3_relation":[{"sense":"precedence"}]},{"pdtb3_relation":[{"sense":"conjunction"}]},{"pdtb3_relation":[{"sense":"cause_result"}]}]}]},{"id":"c137","word":"тож","english_equivalent":{"t":"so"},"orths":{"orth":[{"type":"cont","canonical":1,"onr":"137o1","part":[{"type":"single","t":"тож"}]}]},"syn":[{"cat":{"t":"subord_conj"},"sem":[{"pdtb3_relation":[{"sense":"cause_result"}]}]}]},{"id":"c138","word":"тому","english_equivalent":{"t":"so"},"orths":{"orth":[{"type":"cont","canonical":1,"onr":"138o1","part":[{"type":"single","t":"тому"}]}]},"syn":[{"cat":{"t":"adverb"},"sem":[{"pdtb3_relation":[{"sense":"cause_result"}]}]}]},{"id":"c139","word":"тому що","english_equivalent":{"t":"because"},"orths":{"orth":[{"type":"cont","canonical":1,"onr":"139o1","part":[{"type":"single","t":"тому що"}]}]},"syn":[{"cat":{"t":"subord_conj"},"sem":[{"pdtb3_relation":[{"sense":"cause_reason"}]}]}]},{"id":"c140","word":"тому-то","english_equivalent":{"t":"because of that, that is why"},"orths":{"orth":[{"type":"cont","canonical":1,"onr":"140o1","part":[{"type":"single","t":"тому-то"}]}]},"syn":[{"cat":{"t":"subord_conj"},"sem":[{"pdtb3_relation":[{"sense":"cause_result"}]}]}]},{"id":"c141","word":"точніше","english_equivalent":{"t":"specifically"},"orths":{"orth":[{"type":"cont","canonical":1,"onr":"141o1","part":[{"type":"single","t":"точніше"}]}]},"syn":[{"cat":{"t":"adverb"},"sem":[{"pdtb3_relation":[{"sense":"level-of-detail_arg2-as-detail"}]},{"pdtb3_relation":[{"sense":"conjunction"}]}]}]},{"id":"c142","word":"у зв'язку з","english_equivalent":{"t":"in connection with"},"orths":{"orth":[{"type":"cont","canonical":1,"onr":"142o1","part":[{"type":"phrasal","t":"у зв'язку з"}]},{"type":"cont","canonical":0,"onr":"142o2","part":[{"type":"phrasal","t":"в зв'язку з"}]}]},"syn":[{"cat":{"t":"preposition"},"sem":[{"pdtb3_relation":[{"sense":"cause_reason"}]},{"pdtb3_relation":[{"sense":"exception_arg1-as-excpt"}]},{"pdtb3_relation":[{"sense":"precedence"}]}]}]},{"id":"c143","word":"у свою чергу","english_equivalent":{"t":"in turn"},"orths":{"orth":[{"type":"cont","canonical":1,"onr":"143o1","part":[{"type":"phrasal","t":"у свою чергу"}]},{"type":"cont","canonical":0,"onr":"143o2","part":[{"type":"phrasal","t":"в свою чергу"}]}]},"syn":[{"cat":{"t":"adverb"},"sem":[{"pdtb3_relation":[{"sense":"contrast"}]},{"pdtb3_relation":[{"sense":"succession"}]}]}]},{"id":"c144","word":"у той час як","english_equivalent":{"t":"while, whilst"},"orths":{"orth":[{"type":"cont","canonical":1,"onr":"144o1","part":[{"type":"phrasal","t":"у той час як"}]},{"type":"cont","canonical":0,"onr":"144o2","part":[{"type":"phrasal","t":"в той час як"}]}]},"syn":[{"cat":{"t":"subord_conj"},"sem":[{"pdtb3_relation":[{"sense":"synchronous"}]},{"pdtb3_relation":[{"sense":"contrast"}]}]}]},{"id":"c145","word":"фактично","english_equivalent":{"t":"in fact"},"orths":{"orth":[{"type":"cont","canonical":1,"onr":"145o1","part":[{"type":"single","t":"фактично"}]}]},"syn":[{"cat":{"t":"adverb"},"sem":[{"pdtb3_relation":[{"sense":"level-of-detail_arg1-as-detail"}]},{"pdtb3_relation":[{"sense":"instantiation_arg2-as-instance"}]},{"pdtb3_relation":[{"sense":"conjunction"}]}]}]},{"id":"c146","word":"хай","english_equivalent":{"t":"so that"},"orths":{"orth":[{"type":"cont","canonical":1,"onr":"146o1","part":[{"type":"single","t":"хай"}]},{"type":"cont","canonical":0,"onr":"146o2","part":[{"type":"single","t":"хай-но"}]}]},"syn":[{"cat":{"t":"subord_conj"},"sem":[{"pdtb3_relation":[{"sense":"concession_arg1-as-denier"}]}]}]},{"id":"c147","word":"хіба","english_equivalent":{"t":"unless"},"orths":{"orth":[{"type":"cont","canonical":1,"onr":"147o1","part":[{"type":"single","t":"хіба"}]}]},"syn":[{"cat":{"t":"subord_conj"},"sem":[{"pdtb3_relation":[{"sense":"negCondition_arg2-as-negCond"}]}]}]},{"id":"c148","word":"хіба що","english_equivalent":{"t":"unless"},"orths":{"orth":[{"type":"cont","canonical":1,"onr":"148o1","part":[{"type":"phrasal","t":"хіба що"}]}]},"syn":[{"cat":{"t":"subord_conj"},"sem":[{"pdtb3_relation":[{"sense":"negCondition_arg2-as-negCond"}]},{"pdtb3_relation":[{"sense":"exception_arg1-as-excpt"}]}]}]},{"id":"c149","word":"хоч","english_equivalent":{"t":"though"},"orths":{"orth":[{"type":"cont","canonical":1,"onr":"149o1","part":[{"type":"single","t":"хоч"}]}]},"syn":[{"cat":{"t":"preposition"},"sem":[{"pdtb3_relation":[{"sense":"concession_arg1-as-denier"}]}]}]},{"id":"c150","word":"хоча","english_equivalent":{"t":"though"},"orths":{"orth":[{"type":"cont","canonical":1,"onr":"150o1","part":[{"type":"single","t":"хоча"}]}]},"syn":[{"cat":{"t":"subord_conj"},"sem":[{"pdtb3_relation":[{"sense":"contrast"}]},{"pdtb3_relation":[{"sense":"exception_arg2-as-excpt"}]}]}]},{"id":"c151","word":"цебто","english_equivalent":{"t":"namely,that is"},"orths":{"orth":[{"type":"cont","canonical":1,"onr":"151o1","part":[{"type":"single","t":"цебто"}]}]},"syn":[{"cat":{"t":"coord_conj"},"sem":[{"pdtb3_relation":[{"sense":"equivalence"}]}]}]},{"id":"c152","word":"через","english_equivalent":{"t":"because"},"orths":{"orth":[{"type":"cont","canonical":1,"onr":"152o1","part":[{"type":"single","t":"через"}]}]},"syn":[{"cat":{"t":"preposition"},"sem":[{"pdtb3_relation":[{"sense":"cause_reason"}]}]}]},{"id":"c153","word":"чи","english_equivalent":{"t":"or"},"orths":{"orth":[{"type":"cont","canonical":1,"onr":"153o1","part":[{"type":"single","t":"чи"}]}]},"syn":[{"cat":{"t":"subord_conj"},"sem":[{"pdtb3_relation":[{"sense":"contrast"}]},{"pdtb3_relation":[{"sense":"disjunction"}]},{"pdtb3_relation":[{"sense":"conjunction"}]}]}]},{"id":"c154","word":"ще","english_equivalent":{"t":"still"},"orths":{"orth":[{"type":"cont","canonical":1,"onr":"154o1","part":[{"type":"single","t":"ще"}]}]},"syn":[{"cat":{"t":"adverb"},"sem":[{"pdtb3_relation":[{"sense":"conjunction"}]},{"pdtb3_relation":[{"sense":"instantiation_arg1-as-instance"}]},{"pdtb3_relation":[{"sense":"concession_arg2-as-denier"}]}]}]},{"id":"c155","word":"щоби","english_equivalent":{"t":"in order to"},"orths":{"orth":[{"type":"cont","canonical":1,"onr":"155o1","part":[{"type":"single","t":"щоби"}]},{"type":"cont","canonical":0,"onr":"155o2","part":[{"type":"single","t":"щоб"}]}]},"syn":[{"cat":{"t":"subord_conj"},"sem":[{"pdtb3_relation":[{"sense":"purpose_arg2-as-goal"}]}]}]},{"id":"c156","word":"щойно","english_equivalent":{"t":"as soon as"},"orths":{"orth":[{"type":"cont","canonical":1,"onr":"156o1","part":[{"type":"single","t":"щойно"}]}]},"syn":[{"cat":{"t":"subord_conj"},"sem":[{"pdtb3_relation":[{"sense":"synchronous"}]}]}]},{"id":"c157","word":"щодо","english_equivalent":{"t":"speaking about"},"orths":{"orth":[{"type":"cont","canonical":1,"onr":"157o1","part":[{"type":"single","t":"щодо"}]},{"type":"cont","canonical":0,"onr":"157o2","part":[{"type":"single","t":"а щодо...то"}]}]},"syn":[{"cat":{"t":"other"},"sem":[{"pdtb3_relation":[{"sense":"instantiation_arg1-as-instance"}]}]}]},{"id":"c158","word":"щоправда","english_equivalent":{"t":"though"},"orths":{"orth":[{"type":"cont","canonical":1,"onr":"158o1","part":[{"type":"single","t":"щоправда"}]}]},"syn":[{"cat":{"t":"subord_conj"},"sem":[{"pdtb3_relation":[{"sense":"concession_arg1-as-denier"}]}]}]},{"id":"c159","word":"як","english_equivalent":{"t":"as, when"},"orths":{"orth":[{"type":"cont","canonical":1,"onr":"159o1","part":[{"type":"single","t":"як"}]}]},"syn":[{"cat":{"t":"preposition"},"sem":[{"pdtb3_relation":[{"sense":"equivalence"}]},{"pdtb3_relation":[{"sense":"condition_arg2-as-cond"}]}]}]},{"id":"c160","word":"як тільки","english_equivalent":{"t":"unless, as soon as"},"orths":{"orth":[{"type":"cont","canonical":1,"onr":"160o1","part":[{"type":"phrasal","t":"як тільки"}]}]},"syn":[{"cat":{"t":"subord_conj"},"sem":[{"pdtb3_relation":[{"sense":"succession"}]},{"pdtb3_relation":[{"sense":"synchronous"}]}]}]},{"id":"c161","word":"якби","english_equivalent":{"t":"if"},"orths":{"orth":[{"type":"cont","canonical":1,"onr":"161o1","part":[{"type":"single","t":"якби"}]},{"type":"cont","canonical":0,"onr":"161o2","part":[{"type":"single","t":"якби...то"}]}]},"syn":[{"cat":{"t":"subord_conj"},"sem":[{"pdtb3_relation":[{"sense":"concession_arg1-as-denier"}]},{"pdtb3_relation":[{"sense":"condition_arg2-as-cond"}]},{"pdtb3_relation":[{"sense":"cause_result"}]}]}]},{"id":"c162","word":"якби не","english_equivalent":{"t":"if not, unless, but for"},"orths":{"orth":[{"type":"cont","canonical":1,"onr":"162o1","part":[{"type":"phrasal","t":"якби не"}]}]},"syn":[{"cat":{"t":"subord_conj"},"sem":[{"pdtb3_relation":[{"sense":"concession_arg1-as-denier"}]},{"pdtb3_relation":[{"sense":"condition_arg2-as-cond"}]},{"pdtb3_relation":[{"sense":"cause_negResult"}]}]}]},{"id":"c163","word":"якщо","english_equivalent":{"t":"if"},"orths":{"orth":[{"type":"cont","canonical":1,"onr":"163o1","part":[{"type":"single","t":"якщо"}]},{"type":"cont","canonical":0,"onr":"163o2","part":[{"type":"single","t":"якщо...то"}]}]},"syn":[{"cat":{"t":"subord_conj"},"sem":[{"pdtb3_relation":[{"sense":"condition_arg2-as-cond"}]},{"pdtb3_relation":[{"sense":"cause_reason"}]}]}]}]}